RosGazeboLibrary/Gazebo.py
RosGazeboLibrary/ROS.py
RosGazeboLibrary/__init__.py
robotframework_rosgazebolibrary-0.0.5.dist-info/LICENSE
robotframework_rosgazebolibrary-0.0.5.dist-info/METADATA
robotframework_rosgazebolibrary-0.0.5.dist-info/NOTICE
robotframework_rosgazebolibrary-0.0.5.dist-info/WHEEL
robotframework_rosgazebolibrary-0.0.5.dist-info/top_level.txt
robotframework_rosgazebolibrary-0.0.5.dist-info/RECORD
