Metadata-Version: 2.1
Name: robotframework-rosgazebolibrary
Version: 0.0.5
Summary: Keyword library for the Robot Framework for accessing ROS based systems and the Gazebo simulator.
Home-page: https://github.com/hielsnoppe/robotframework-rosgazebolibrary
Author: Niels Hoppe
Author-email: niels.hoppe@fokus.fraunhofer.de
License: UNKNOWN
Project-URL: Bug Tracker, https://github.com/hielsnoppe/robotframework-rosgazebolibrary/issues
Platform: UNKNOWN
Classifier: Development Status :: 3 - Alpha
Classifier: Framework :: Robot Framework :: Library
Classifier: Intended Audience :: Manufacturing
Classifier: Intended Audience :: Science/Research
Classifier: License :: OSI Approved :: Apache Software License
Classifier: Programming Language :: Python :: 3
Classifier: Topic :: Scientific/Engineering
Classifier: Topic :: Software Development :: Testing
Requires-Python: >=3.6
License-File: LICENSE
License-File: NOTICE
Requires-Dist: robotframework (>=4.1.3)
Requires-Dist: roslibpy (>=1.3.0)
